sql_exercise_generator/Generator.py
sql_exercise_generator/__init__.py
dbis_sql_exercise_generator-0.0.1.dist-info/LICENCE
dbis_sql_exercise_generator-0.0.1.dist-info/METADATA
dbis_sql_exercise_generator-0.0.1.dist-info/WHEEL
dbis_sql_exercise_generator-0.0.1.dist-info/top_level.txt
dbis_sql_exercise_generator-0.0.1.dist-info/RECORD
