Metadata-Version: 2.1
Name: dbis-sql-exercise-generator
Version: 0.0.1
Summary: RWTH Aachen Computer Science i5/dbis assets for Lecture Datenbanken und Informationssysteme
Author-email: Til Mohr <til.mohr@rwth-aachen.de>
Project-URL: Homepage, https://git.rwth-aachen.de/i5/teaching/dbis/dbis-sql-exercise-generator
Classifier: Programming Language :: Python :: 3.10
Classifier: Programming Language :: Python :: 3.11
Requires-Python: >=3.10
License-File: LICENCE
Requires-Dist: docstring-inheritance
Requires-Dist: typeguard
Requires-Dist: dbis-exc-manager
Requires-Dist: Jinja2
